{"@context":"https://iiif.io/api/presentation/3/context.json","id":"https://markpbaggett.github.io/canopy-vol-voices/api/facet/subject/bicycles-tennessee-clarksville.json","type":"Collection","label":{"none":["Bicycles--Tennessee--Clarksville"]},"items":[{"id":"https://digital.lib.utk.edu/assemble/manifest/volvoices/2362","type":"Manifest","label":{"en":["Bicycle Enthusiast"]},"thumbnail":[{"id":"https://digital.lib.utk.edu/iiif/2/collections~islandora~object~volvoices%3A2362~datastream~JP2/full/321,471/0/default.jpg","width":321,"height":471,"type":"Image","format":"image/jpeg","service":[{"@id":"https://digital.lib.utk.edu/iiif/2/collections~islandora~object~volvoices%3A2362~datastream~JP2","@type":"http://iiif.io/api/image/2/context.json","profile":"http://iiif.io/api/image/2/level2.json"}]}],"homepage":[{"id":"https://markpbaggett.github.io/canopy-vol-voices/works/bicycle-enthusiast","type":"Text","label":{"en":["Bicycle Enthusiast"]}}]}],"partOf":[{"id":"https://markpbaggett.github.io/canopy-vol-voices/api/facet/subject.json","type":"Collection"}],"summary":{"none":["Subject"]},"homepage":[{"id":"https://markpbaggett.github.io/canopy-vol-voices/search?subject=bicycles-tennessee-clarksville","type":"Text","label":{"none":["Bicycles--Tennessee--Clarksville"]}}]}