{"@context":"https://iiif.io/api/presentation/3/context.json","id":"https://markpbaggett.github.io/canopy-vol-voices/api/facet/subject/cherokee-indians-legal-status-laws-etc.json","type":"Collection","label":{"none":["Cherokee Indians -- Legal status, laws, etc."]},"items":[{"id":"https://digital.lib.utk.edu/assemble/manifest/volvoices/13095","type":"Manifest","label":{"en":["1843 Nov. 3 [of] David Taylor and Gideon Morgan"]},"thumbnail":[{"id":"https://digital.lib.utk.edu/collections/islandora/object/volvoices%3A13095/datastream/TN","width":200,"height":200,"type":"Image","format":"image/jpeg"}],"homepage":[{"id":"https://markpbaggett.github.io/canopy-vol-voices/works/1843-nov-3-of-david-taylor-and-gideon-morgan","type":"Text","label":{"en":["1843 Nov. 3 [of] David Taylor and Gideon Morgan"]}}]},{"id":"https://digital.lib.utk.edu/assemble/manifest/volvoices/13149","type":"Manifest","label":{"en":["1820 May 1 [between] Rhea County Court and Lewis Ross"]},"thumbnail":[{"id":"https://digital.lib.utk.edu/collections/islandora/object/volvoices%3A13149/datastream/TN","width":200,"height":200,"type":"Image","format":"image/jpeg"}],"homepage":[{"id":"https://markpbaggett.github.io/canopy-vol-voices/works/1820-may-1-between-rhea-county-court-and-lewis-ross","type":"Text","label":{"en":["1820 May 1 [between] Rhea County Court and Lewis Ross"]}}]},{"id":"https://digital.lib.utk.edu/assemble/manifest/volvoices/13250","type":"Manifest","label":{"en":["1837 Feb. between Spencer Jarnagin and the Cherokee Nation East"]},"thumbnail":[{"id":"https://digital.lib.utk.edu/collections/islandora/object/volvoices%3A13250/datastream/TN","width":200,"height":200,"type":"Image","format":"image/jpeg"}],"homepage":[{"id":"https://markpbaggett.github.io/canopy-vol-voices/works/1837-feb-between-spencer-jarnagin-and-the-cherokee-nation-east","type":"Text","label":{"en":["1837 Feb. between Spencer Jarnagin and the Cherokee Nation East"]}}]},{"id":"https://digital.lib.utk.edu/assemble/manifest/volvoices/13651","type":"Manifest","label":{"en":["Constitution of the Cherokee Nation, 1827 Jul. 24, New Town Echota"]},"thumbnail":[{"id":"https://digital.lib.utk.edu/collections/islandora/object/volvoices%3A13651/datastream/TN","width":200,"height":200,"type":"Image","format":"image/jpeg"}],"homepage":[{"id":"https://markpbaggett.github.io/canopy-vol-voices/works/constitution-of-the-cherokee-nation-1827-jul-24-new-town-echota","type":"Text","label":{"en":["Constitution of the Cherokee Nation, 1827 Jul. 24, New Town Echota"]}}]}],"partOf":[{"id":"https://markpbaggett.github.io/canopy-vol-voices/api/facet/subject.json","type":"Collection"}],"summary":{"none":["Subject"]},"homepage":[{"id":"https://markpbaggett.github.io/canopy-vol-voices/search?subject=cherokee-indians-legal-status-laws-etc","type":"Text","label":{"none":["Cherokee Indians -- Legal status, laws, etc."]}}]}