{"@context":"https://iiif.io/api/presentation/3/context.json","id":"https://markpbaggett.github.io/canopy-vol-voices/api/facet/subject/coffee-general-john.json","type":"Collection","label":{"none":["Coffee, General John."]},"items":[{"id":"https://digital.lib.utk.edu/assemble/manifest/volvoices/14156","type":"Manifest","label":{"en":["[Letter] 1819 Aug. 20 [to] Gen[era]l John Coffee"]},"thumbnail":[{"id":"https://digital.lib.utk.edu/collections/islandora/object/volvoices%3A14156/datastream/TN","width":200,"height":200,"type":"Image","format":"image/jpeg"}],"homepage":[{"id":"https://markpbaggett.github.io/canopy-vol-voices/works/letter-1819-aug-20-to-general-john-coffee","type":"Text","label":{"en":["[Letter] 1819 Aug. 20 [to] Gen[era]l John Coffee"]}}]}],"partOf":[{"id":"https://markpbaggett.github.io/canopy-vol-voices/api/facet/subject.json","type":"Collection"}],"summary":{"none":["Subject"]},"homepage":[{"id":"https://markpbaggett.github.io/canopy-vol-voices/search?subject=coffee-general-john","type":"Text","label":{"none":["Coffee, General John."]}}]}