{"@context":"https://iiif.io/api/presentation/3/context.json","id":"https://markpbaggett.github.io/canopy-vol-voices/api/facet/subject/compensation.json","type":"Collection","label":{"none":["Compensation."]},"items":[{"id":"https://digital.lib.utk.edu/assemble/manifest/volvoices/15163","type":"Manifest","label":{"en":["George Smith v. United States"]},"thumbnail":[{"id":"https://digital.lib.utk.edu/collections/islandora/object/volvoices%3A15163/datastream/TN","width":200,"height":200,"type":"Image","format":"image/jpeg"}],"homepage":[{"id":"https://markpbaggett.github.io/canopy-vol-voices/works/george-smith-v-united-states","type":"Text","label":{"en":["George Smith v. United States"]}}]}],"partOf":[{"id":"https://markpbaggett.github.io/canopy-vol-voices/api/facet/subject.json","type":"Collection"}],"summary":{"none":["Subject"]},"homepage":[{"id":"https://markpbaggett.github.io/canopy-vol-voices/search?subject=compensation","type":"Text","label":{"none":["Compensation."]}}]}