{"@context":"https://iiif.io/api/presentation/3/context.json","id":"https://markpbaggett.github.io/canopy-vol-voices/api/facet/subject/executive-orders.json","type":"Collection","label":{"none":["Executive orders ."]},"items":[{"id":"https://digital.lib.utk.edu/assemble/manifest/volvoices/13642","type":"Manifest","label":{"en":["Orders No. 25, 1838 May 17, Eastern Division, Cherokee Agency, Ten[nessee]"]},"thumbnail":[{"id":"https://digital.lib.utk.edu/collections/islandora/object/volvoices%3A13642/datastream/TN","width":200,"height":200,"type":"Image","format":"image/jpeg"}],"homepage":[{"id":"https://markpbaggett.github.io/canopy-vol-voices/works/orders-no-25-1838-may-17-eastern-division-cherokee-agency-tennessee","type":"Text","label":{"en":["Orders No. 25, 1838 May 17, Eastern Division, Cherokee Agency, Ten[nessee]"]}}]}],"partOf":[{"id":"https://markpbaggett.github.io/canopy-vol-voices/api/facet/subject.json","type":"Collection"}],"summary":{"none":["Subject"]},"homepage":[{"id":"https://markpbaggett.github.io/canopy-vol-voices/search?subject=executive-orders","type":"Text","label":{"none":["Executive orders ."]}}]}