{"@context":"https://iiif.io/api/presentation/3/context.json","id":"https://markpbaggett.github.io/canopy-vol-voices/api/facet/subject/gore-anderson-farm-bill.json","type":"Collection","label":{"none":["Gore-Anderson Farm Bill."]},"items":[{"id":"https://digital.lib.utk.edu/assemble/manifest/volvoices/8587","type":"Manifest","label":{"en":["Farm Policy Campaign Speech"]},"thumbnail":[{"id":"https://digital.lib.utk.edu/collections/islandora/object/volvoices%3A8587/datastream/TN","width":200,"height":200,"type":"Image","format":"image/jpeg"}],"homepage":[{"id":"https://markpbaggett.github.io/canopy-vol-voices/works/farm-policy-campaign-speech","type":"Text","label":{"en":["Farm Policy Campaign Speech"]}}]}],"partOf":[{"id":"https://markpbaggett.github.io/canopy-vol-voices/api/facet/subject.json","type":"Collection"}],"summary":{"none":["Subject"]},"homepage":[{"id":"https://markpbaggett.github.io/canopy-vol-voices/search?subject=gore-anderson-farm-bill","type":"Text","label":{"none":["Gore-Anderson Farm Bill."]}}]}