{"@context":"https://iiif.io/api/presentation/3/context.json","id":"https://markpbaggett.github.io/canopy-vol-voices/api/facet/subject/horses-2.json","type":"Collection","label":{"none":["Horses."]},"items":[{"id":"https://digital.lib.utk.edu/assemble/manifest/volvoices/14756","type":"Manifest","label":{"en":["1831 Mar. 5 [to] Hardy Moore"]},"thumbnail":[{"id":"https://digital.lib.utk.edu/collections/islandora/object/volvoices%3A14756/datastream/TN","width":200,"height":200,"type":"Image","format":"image/jpeg"}],"homepage":[{"id":"https://markpbaggett.github.io/canopy-vol-voices/works/1831-mar-5-to-hardy-moore","type":"Text","label":{"en":["1831 Mar. 5 [to] Hardy Moore"]}}]},{"id":"https://digital.lib.utk.edu/assemble/manifest/volvoices/14768","type":"Manifest","label":{"en":["1831, [to] William"]},"thumbnail":[{"id":"https://digital.lib.utk.edu/collections/islandora/object/volvoices%3A14768/datastream/TN","width":200,"height":200,"type":"Image","format":"image/jpeg"}],"homepage":[{"id":"https://markpbaggett.github.io/canopy-vol-voices/works/1831-to-william","type":"Text","label":{"en":["1831, [to] William"]}}]}],"partOf":[{"id":"https://markpbaggett.github.io/canopy-vol-voices/api/facet/subject.json","type":"Collection"}],"summary":{"none":["Subject"]},"homepage":[{"id":"https://markpbaggett.github.io/canopy-vol-voices/search?subject=horses-2","type":"Text","label":{"none":["Horses."]}}]}