{"@context":"https://iiif.io/api/presentation/3/context.json","id":"https://markpbaggett.github.io/canopy-vol-voices/api/facet/subject/indians-of-north-america-2.json","type":"Collection","label":{"none":["Indians of North America ."]},"items":[{"id":"https://digital.lib.utk.edu/assemble/manifest/volvoices/13029","type":"Manifest","label":{"en":["1803 Jul. 1, [to] Sam[ue]l Hanson [and] Tho[ma]s Hayword"]},"thumbnail":[{"id":"https://digital.lib.utk.edu/collections/islandora/object/volvoices%3A13029/datastream/TN","width":200,"height":200,"type":"Image","format":"image/jpeg"}],"homepage":[{"id":"https://markpbaggett.github.io/canopy-vol-voices/works/1803-jul-1-to-samuel-hanson-and-thomas-hayword","type":"Text","label":{"en":["1803 Jul. 1, [to] Sam[ue]l Hanson [and] Tho[ma]s Hayword"]}}]}],"partOf":[{"id":"https://markpbaggett.github.io/canopy-vol-voices/api/facet/subject.json","type":"Collection"}],"summary":{"none":["Subject"]},"homepage":[{"id":"https://markpbaggett.github.io/canopy-vol-voices/search?subject=indians-of-north-america-2","type":"Text","label":{"none":["Indians of North America ."]}}]}