{"@context":"https://iiif.io/api/presentation/3/context.json","id":"https://markpbaggett.github.io/canopy-vol-voices/api/facet/subject/karig-walter-1898-1956.json","type":"Collection","label":{"none":["Karig, Walter, 1898-1956."]},"items":[{"id":"https://digital.lib.utk.edu/assemble/manifest/volvoices/8108","type":"Manifest","label":{"en":["Liberty"]},"thumbnail":[{"id":"https://digital.lib.utk.edu/collections/islandora/object/volvoices%3A8108/datastream/TN","width":200,"height":200,"type":"Image","format":"image/jpeg"}],"homepage":[{"id":"https://markpbaggett.github.io/canopy-vol-voices/works/liberty","type":"Text","label":{"en":["Liberty"]}}]}],"partOf":[{"id":"https://markpbaggett.github.io/canopy-vol-voices/api/facet/subject.json","type":"Collection"}],"summary":{"none":["Subject"]},"homepage":[{"id":"https://markpbaggett.github.io/canopy-vol-voices/search?subject=karig-walter-1898-1956","type":"Text","label":{"none":["Karig, Walter, 1898-1956."]}}]}