{"@context":"https://iiif.io/api/presentation/3/context.json","id":"https://markpbaggett.github.io/canopy-vol-voices/api/facet/subject/polk-county-courthouse.json","type":"Collection","label":{"none":["Polk County Courthouse."]},"items":[{"id":"https://digital.lib.utk.edu/assemble/manifest/volvoices/11834","type":"Manifest","label":{"en":["Images of the Polk County courthouse"]},"thumbnail":[{"id":"https://digital.lib.utk.edu/collections/islandora/object/volvoices%3A11834/datastream/TN","width":200,"height":200,"type":"Image","format":"image/jpeg"}],"homepage":[{"id":"https://markpbaggett.github.io/canopy-vol-voices/works/images-of-the-polk-county-courthouse","type":"Text","label":{"en":["Images of the Polk County courthouse"]}}]}],"partOf":[{"id":"https://markpbaggett.github.io/canopy-vol-voices/api/facet/subject.json","type":"Collection"}],"summary":{"none":["Subject"]},"homepage":[{"id":"https://markpbaggett.github.io/canopy-vol-voices/search?subject=polk-county-courthouse","type":"Text","label":{"none":["Polk County Courthouse."]}}]}