{"@context":"https://iiif.io/api/presentation/3/context.json","id":"https://markpbaggett.github.io/canopy-vol-voices/api/facet/subject/trail-of-tears-1838.json","type":"Collection","label":{"none":["Trail of Tears, 1838 ."]},"items":[{"id":"https://digital.lib.utk.edu/assemble/manifest/volvoices/13257","type":"Manifest","label":{"en":["1838 Sep. 18, Coosawattee District, The United States to Ratting Gourd"]},"thumbnail":[{"id":"https://digital.lib.utk.edu/collections/islandora/object/volvoices%3A13257/datastream/TN","width":200,"height":200,"type":"Image","format":"image/jpeg"}],"homepage":[{"id":"https://markpbaggett.github.io/canopy-vol-voices/works/1838-sep-18-coosawattee-district-the-united-states-to-ratting-gourd","type":"Text","label":{"en":["1838 Sep. 18, Coosawattee District, The United States to Ratting Gourd"]}}]},{"id":"https://digital.lib.utk.edu/assemble/manifest/volvoices/13261","type":"Manifest","label":{"en":["1838 Sep. 18, The United States to Ratting Gourd"]},"thumbnail":[{"id":"https://digital.lib.utk.edu/collections/islandora/object/volvoices%3A13261/datastream/TN","width":200,"height":200,"type":"Image","format":"image/jpeg"}],"homepage":[{"id":"https://markpbaggett.github.io/canopy-vol-voices/works/1838-sep-18-the-united-states-to-ratting-gourd","type":"Text","label":{"en":["1838 Sep. 18, The United States to Ratting Gourd"]}}]}],"partOf":[{"id":"https://markpbaggett.github.io/canopy-vol-voices/api/facet/subject.json","type":"Collection"}],"summary":{"none":["Subject"]},"homepage":[{"id":"https://markpbaggett.github.io/canopy-vol-voices/search?subject=trail-of-tears-1838","type":"Text","label":{"none":["Trail of Tears, 1838 ."]}}]}