{"@context":"https://iiif.io/api/presentation/3/context.json","id":"https://markpbaggett.github.io/canopy-vol-voices/api/facet/subject/united-states-civil-war-1860-1865-songs-and-music.json","type":"Collection","label":{"none":["United States Civil War 1860-1865 -- Songs and music."]},"items":[{"id":"https://digital.lib.utk.edu/assemble/manifest/volvoices/11392","type":"Manifest","label":{"en":["Union March"]},"thumbnail":[{"id":"https://digital.lib.utk.edu/collections/islandora/object/volvoices%3A11392/datastream/TN","width":200,"height":200,"type":"Image","format":"image/jpeg"}],"homepage":[{"id":"https://markpbaggett.github.io/canopy-vol-voices/works/union-march","type":"Text","label":{"en":["Union March"]}}]}],"partOf":[{"id":"https://markpbaggett.github.io/canopy-vol-voices/api/facet/subject.json","type":"Collection"}],"summary":{"none":["Subject"]},"homepage":[{"id":"https://markpbaggett.github.io/canopy-vol-voices/search?subject=united-states-civil-war-1860-1865-songs-and-music","type":"Text","label":{"none":["United States Civil War 1860-1865 -- Songs and music."]}}]}