{"@context":"https://iiif.io/api/presentation/3/context.json","id":"https://markpbaggett.github.io/canopy-vol-voices/api/facet/subject/universities-and-colleges-tennessee.json","type":"Collection","label":{"none":["Universities and colleges -- Tennessee."]},"items":[{"id":"https://digital.lib.utk.edu/assemble/manifest/volvoices/8668","type":"Manifest","label":{"en":["West Tennessee College catalogue 1844"]},"thumbnail":[{"id":"https://digital.lib.utk.edu/collections/islandora/object/volvoices%3A8668/datastream/TN","width":200,"height":200,"type":"Image","format":"image/jpeg"}],"homepage":[{"id":"https://markpbaggett.github.io/canopy-vol-voices/works/west-tennessee-college-catalogue-1844","type":"Text","label":{"en":["West Tennessee College catalogue 1844"]}}]}],"partOf":[{"id":"https://markpbaggett.github.io/canopy-vol-voices/api/facet/subject.json","type":"Collection"}],"summary":{"none":["Subject"]},"homepage":[{"id":"https://markpbaggett.github.io/canopy-vol-voices/search?subject=universities-and-colleges-tennessee","type":"Text","label":{"none":["Universities and colleges -- Tennessee."]}}]}