{"@context":"https://iiif.io/api/presentation/3/context.json","id":"https://markpbaggett.github.io/canopy-vol-voices/api/facet/subject/washington-booker-t-1856-1915.json","type":"Collection","label":{"none":["Washington, Booker T., 1856-1915."]},"items":[{"id":"https://digital.lib.utk.edu/assemble/manifest/volvoices/8311","type":"Manifest","label":{"en":["Booker T. Washington in Tuskegee, AL, to R. R. Church, Jr. in Memphis, TN"]},"thumbnail":[{"id":"https://digital.lib.utk.edu/collections/islandora/object/volvoices%3A8311/datastream/TN","width":200,"height":200,"type":"Image","format":"image/jpeg"}],"homepage":[{"id":"https://markpbaggett.github.io/canopy-vol-voices/works/booker-t-washington-in-tuskegee-al-to-r-r-church-jr-in-memphis-tn","type":"Text","label":{"en":["Booker T. Washington in Tuskegee, AL, to R. R. Church, Jr. in Memphis, TN"]}}]},{"id":"https://digital.lib.utk.edu/assemble/manifest/volvoices/8326","type":"Manifest","label":{"en":["National Negro Business League Membership certificate"]},"thumbnail":[{"id":"https://digital.lib.utk.edu/collections/islandora/object/volvoices%3A8326/datastream/TN","width":200,"height":200,"type":"Image","format":"image/jpeg"}],"homepage":[{"id":"https://markpbaggett.github.io/canopy-vol-voices/works/national-negro-business-league-membership-certificate","type":"Text","label":{"en":["National Negro Business League Membership certificate"]}}]},{"id":"https://digital.lib.utk.edu/assemble/manifest/volvoices/8328","type":"Manifest","label":{"en":["Booker T. Washington in Tuskegee, AL, to R. R. Church, Sr. in Memphis, TN"]},"thumbnail":[{"id":"https://digital.lib.utk.edu/collections/islandora/object/volvoices%3A8328/datastream/TN","width":200,"height":200,"type":"Image","format":"image/jpeg"}],"homepage":[{"id":"https://markpbaggett.github.io/canopy-vol-voices/works/booker-t-washington-in-tuskegee-al-to-r-r-church-sr-in-memphis-tn","type":"Text","label":{"en":["Booker T. Washington in Tuskegee, AL, to R. R. Church, Sr. in Memphis, TN"]}}]}],"partOf":[{"id":"https://markpbaggett.github.io/canopy-vol-voices/api/facet/subject.json","type":"Collection"}],"summary":{"none":["Subject"]},"homepage":[{"id":"https://markpbaggett.github.io/canopy-vol-voices/search?subject=washington-booker-t-1856-1915","type":"Text","label":{"none":["Washington, Booker T., 1856-1915."]}}]}