{"@context":"https://iiif.io/api/presentation/3/context.json","id":"https://markpbaggett.github.io/canopy-vol-voices/api/facet/place/alexandria-la.json","type":"Collection","label":{"none":["Alexandria (LA)"]},"items":[{"id":"https://digital.lib.utk.edu/assemble/manifest/volvoices/14582","type":"Manifest","label":{"en":["1850 Dec. 24 [to] James King"]},"thumbnail":[{"id":"https://digital.lib.utk.edu/collections/islandora/object/volvoices%3A14582/datastream/TN","width":200,"height":200,"type":"Image","format":"image/jpeg"}],"homepage":[{"id":"https://markpbaggett.github.io/canopy-vol-voices/works/1850-dec-24-to-james-king","type":"Text","label":{"en":["1850 Dec. 24 [to] James King"]}}]},{"id":"https://digital.lib.utk.edu/assemble/manifest/volvoices/14587","type":"Manifest","label":{"en":["1850 Mar. 7 [to] James King"]},"thumbnail":[{"id":"https://digital.lib.utk.edu/collections/islandora/object/volvoices%3A14587/datastream/TN","width":200,"height":200,"type":"Image","format":"image/jpeg"}],"homepage":[{"id":"https://markpbaggett.github.io/canopy-vol-voices/works/1850-mar-7-to-james-king","type":"Text","label":{"en":["1850 Mar. 7 [to] James King"]}}]},{"id":"https://digital.lib.utk.edu/assemble/manifest/volvoices/14592","type":"Manifest","label":{"en":["1849 Nov. 30, Alexandria, Louisiana [to] James King"]},"thumbnail":[{"id":"https://digital.lib.utk.edu/collections/islandora/object/volvoices%3A14592/datastream/TN","width":200,"height":200,"type":"Image","format":"image/jpeg"}],"homepage":[{"id":"https://markpbaggett.github.io/canopy-vol-voices/works/1849-nov-30-alexandria-louisiana-to-james-king","type":"Text","label":{"en":["1849 Nov. 30, Alexandria, Louisiana [to] James King"]}}]},{"id":"https://digital.lib.utk.edu/assemble/manifest/volvoices/14597","type":"Manifest","label":{"en":["1843 Dec. 20 [to] James King"]},"thumbnail":[{"id":"https://digital.lib.utk.edu/collections/islandora/object/volvoices%3A14597/datastream/TN","width":200,"height":200,"type":"Image","format":"image/jpeg"}],"homepage":[{"id":"https://markpbaggett.github.io/canopy-vol-voices/works/1843-dec-20-to-james-king","type":"Text","label":{"en":["1843 Dec. 20 [to] James King"]}}]},{"id":"https://digital.lib.utk.edu/assemble/manifest/volvoices/14602","type":"Manifest","label":{"en":["1842 Aug. 7 [to] James King"]},"thumbnail":[{"id":"https://digital.lib.utk.edu/collections/islandora/object/volvoices%3A14602/datastream/TN","width":200,"height":200,"type":"Image","format":"image/jpeg"}],"homepage":[{"id":"https://markpbaggett.github.io/canopy-vol-voices/works/1842-aug-7-to-james-king","type":"Text","label":{"en":["1842 Aug. 7 [to] James King"]}}]}],"partOf":[{"id":"https://markpbaggett.github.io/canopy-vol-voices/api/facet/place.json","type":"Collection"}],"summary":{"none":["Place"]},"homepage":[{"id":"https://markpbaggett.github.io/canopy-vol-voices/search?place=alexandria-la","type":"Text","label":{"none":["Alexandria (LA)"]}}]}