{"@context":"https://iiif.io/api/presentation/3/context.json","id":"https://markpbaggett.github.io/canopy-vol-voices/api/facet/place/knoxville-tenn-newspapers.json","type":"Collection","label":{"none":["Knoxville (Tenn.) -- Newspapers"]},"items":[{"id":"https://digital.lib.utk.edu/assemble/manifest/volvoices/4894","type":"Manifest","label":{"en":["Charlton, C.W. in Knoxville, Tennessee to Ramsey, J.G.M. in Salisbury, North Carolina"]},"thumbnail":[{"id":"https://digital.lib.utk.edu/collections/islandora/object/volvoices%3A4894/datastream/TN","width":200,"height":200,"type":"Image","format":"image/jpeg"}],"homepage":[{"id":"https://markpbaggett.github.io/canopy-vol-voices/works/charlton-cw-in-knoxville-tennessee-to-ramsey-jgm-in-salisbury-north-carolina","type":"Text","label":{"en":["Charlton, C.W. in Knoxville, Tennessee to Ramsey, J.G.M. in Salisbury, North Carolina"]}}]},{"id":"https://digital.lib.utk.edu/assemble/manifest/volvoices/9273","type":"Manifest","label":{"en":["Articles from Brownlow`s Knoxville Whig"]},"thumbnail":[{"id":"https://digital.lib.utk.edu/collections/islandora/object/volvoices%3A9273/datastream/TN","width":200,"height":200,"type":"Image","format":"image/jpeg"}],"homepage":[{"id":"https://markpbaggett.github.io/canopy-vol-voices/works/articles-from-brownlows-knoxville-whig","type":"Text","label":{"en":["Articles from Brownlow`s Knoxville Whig"]}}]},{"id":"https://digital.lib.utk.edu/assemble/manifest/volvoices/15767","type":"Manifest","label":{"en":["L.C. Houk in Washinton, D.C. to O.P. Temple"]},"thumbnail":[{"id":"https://digital.lib.utk.edu/collections/islandora/object/volvoices%3A15767/datastream/TN","width":200,"height":200,"type":"Image","format":"image/jpeg"}],"homepage":[{"id":"https://markpbaggett.github.io/canopy-vol-voices/works/lc-houk-in-washinton-dc-to-op-temple","type":"Text","label":{"en":["L.C. Houk in Washinton, D.C. to O.P. Temple"]}}]}],"partOf":[{"id":"https://markpbaggett.github.io/canopy-vol-voices/api/facet/place.json","type":"Collection"}],"summary":{"none":["Place"]},"homepage":[{"id":"https://markpbaggett.github.io/canopy-vol-voices/search?place=knoxville-tenn-newspapers","type":"Text","label":{"none":["Knoxville (Tenn.) -- Newspapers"]}}]}