{"@context":"https://iiif.io/api/presentation/3/context.json","id":"https://markpbaggett.github.io/canopy-vol-voices/api/facet/place/mc043.json","type":"Collection","label":{"none":["mc043."]},"items":[{"id":"https://digital.lib.utk.edu/assemble/manifest/volvoices/14381","type":"Manifest","label":{"en":["1837 Mar. 15, Winchester, Tennessee [to] C[harles] F. and C[arolyn] V. Welcker, Talladega, Ala[bama]"]},"thumbnail":[{"id":"https://digital.lib.utk.edu/collections/islandora/object/volvoices%3A14381/datastream/TN","width":200,"height":200,"type":"Image","format":"image/jpeg"}],"homepage":[{"id":"https://markpbaggett.github.io/canopy-vol-voices/works/1837-mar-15-winchester-tennessee-to-charles-f-and-carolyn-v-welcker-talladega-alabama","type":"Text","label":{"en":["1837 Mar. 15, Winchester, Tennessee [to] C[harles] F. and C[arolyn] V. Welcker, Talladega, Ala[bama]"]}}]}],"partOf":[{"id":"https://markpbaggett.github.io/canopy-vol-voices/api/facet/place.json","type":"Collection"}],"summary":{"none":["Place"]},"homepage":[{"id":"https://markpbaggett.github.io/canopy-vol-voices/search?place=mc043","type":"Text","label":{"none":["mc043."]}}]}