{"@context":"https://iiif.io/api/presentation/3/context.json","id":"https://markpbaggett.github.io/canopy-vol-voices/api/facet/place/pa0043.json","type":"Collection","label":{"none":["pa0043."]},"items":[{"id":"https://digital.lib.utk.edu/assemble/manifest/volvoices/13283","type":"Manifest","label":{"en":["1834 Apr. 9 [Certificates concerning the enrollment of Charles Jones and Edward Welch]"]},"thumbnail":[{"id":"https://digital.lib.utk.edu/collections/islandora/object/volvoices%3A13283/datastream/TN","width":200,"height":200,"type":"Image","format":"image/jpeg"}],"homepage":[{"id":"https://markpbaggett.github.io/canopy-vol-voices/works/1834-apr-9-certificates-concerning-the-enrollment-of-charles-jones-and-edward-welch","type":"Text","label":{"en":["1834 Apr. 9 [Certificates concerning the enrollment of Charles Jones and Edward Welch]"]}}]}],"partOf":[{"id":"https://markpbaggett.github.io/canopy-vol-voices/api/facet/place.json","type":"Collection"}],"summary":{"none":["Place"]},"homepage":[{"id":"https://markpbaggett.github.io/canopy-vol-voices/search?place=pa0043","type":"Text","label":{"none":["pa0043."]}}]}