{"@context":"https://iiif.io/api/presentation/3/context.json","id":"https://markpbaggett.github.io/canopy-vol-voices/api/facet/place/pa0044.json","type":"Collection","label":{"none":["pa0044."]},"items":[{"id":"https://digital.lib.utk.edu/assemble/manifest/volvoices/13281","type":"Manifest","label":{"en":["1836 Feb. 6, Spring Place, GA [to] W[illia]m Schley, Gov[ernor] of Georgia"]},"thumbnail":[{"id":"https://digital.lib.utk.edu/collections/islandora/object/volvoices%3A13281/datastream/TN","width":200,"height":200,"type":"Image","format":"image/jpeg"}],"homepage":[{"id":"https://markpbaggett.github.io/canopy-vol-voices/works/1836-feb-6-spring-place-ga-to-william-schley-governor-of-georgia","type":"Text","label":{"en":["1836 Feb. 6, Spring Place, GA [to] W[illia]m Schley, Gov[ernor] of Georgia"]}}]}],"partOf":[{"id":"https://markpbaggett.github.io/canopy-vol-voices/api/facet/place.json","type":"Collection"}],"summary":{"none":["Place"]},"homepage":[{"id":"https://markpbaggett.github.io/canopy-vol-voices/search?place=pa0044","type":"Text","label":{"none":["pa0044."]}}]}