{"@context":"https://iiif.io/api/presentation/3/context.json","id":"https://markpbaggett.github.io/canopy-vol-voices/api/facet/place/tennessee-politics-and-government-to-1865-2.json","type":"Collection","label":{"none":["Tennessee -- Politics and government -- To 1865 ."]},"items":[{"id":"https://digital.lib.utk.edu/assemble/manifest/volvoices/13681","type":"Manifest","label":{"en":["1794 Sept. 30 [to John Sevier]"]},"thumbnail":[{"id":"https://digital.lib.utk.edu/collections/islandora/object/volvoices%3A13681/datastream/TN","width":200,"height":200,"type":"Image","format":"image/jpeg"}],"homepage":[{"id":"https://markpbaggett.github.io/canopy-vol-voices/works/1794-sept-30-to-john-sevier","type":"Text","label":{"en":["1794 Sept. 30 [to John Sevier]"]}}]},{"id":"https://digital.lib.utk.edu/assemble/manifest/volvoices/13684","type":"Manifest","label":{"en":["1796 Feb. 29, Philadelphia [to] Governor William Blount"]},"thumbnail":[{"id":"https://digital.lib.utk.edu/collections/islandora/object/volvoices%3A13684/datastream/TN","width":200,"height":200,"type":"Image","format":"image/jpeg"}],"homepage":[{"id":"https://markpbaggett.github.io/canopy-vol-voices/works/1796-feb-29-philadelphia-to-governor-william-blount","type":"Text","label":{"en":["1796 Feb. 29, Philadelphia [to] Governor William Blount"]}}]},{"id":"https://digital.lib.utk.edu/assemble/manifest/volvoices/13694","type":"Manifest","label":{"en":["1828 Mar. 14 [to] Governor Samuel Houston, Nashville, Ten [nessee]"]},"thumbnail":[{"id":"https://digital.lib.utk.edu/collections/islandora/object/volvoices%3A13694/datastream/TN","width":200,"height":200,"type":"Image","format":"image/jpeg"}],"homepage":[{"id":"https://markpbaggett.github.io/canopy-vol-voices/works/1828-mar-14-to-governor-samuel-houston-nashville-ten-nessee","type":"Text","label":{"en":["1828 Mar. 14 [to] Governor Samuel Houston, Nashville, Ten [nessee]"]}}]},{"id":"https://digital.lib.utk.edu/assemble/manifest/volvoices/13699","type":"Manifest","label":{"en":["1828 Feb. 3, Paris, [to] Governor Sam Houston, Nashville, Tennessee"]},"thumbnail":[{"id":"https://digital.lib.utk.edu/collections/islandora/object/volvoices%3A13699/datastream/TN","width":200,"height":200,"type":"Image","format":"image/jpeg"}],"homepage":[{"id":"https://markpbaggett.github.io/canopy-vol-voices/works/1828-feb-3-paris-to-governor-sam-houston-nashville-tennessee","type":"Text","label":{"en":["1828 Feb. 3, Paris, [to] Governor Sam Houston, Nashville, Tennessee"]}}]},{"id":"https://digital.lib.utk.edu/assemble/manifest/volvoices/14447","type":"Manifest","label":{"en":["1833 Aug. 18, Mouth of Poplar Creek [to] Geo[rge] L. Welcker, W[est] Point, New York"]},"thumbnail":[{"id":"https://digital.lib.utk.edu/collections/islandora/object/volvoices%3A14447/datastream/TN","width":200,"height":200,"type":"Image","format":"image/jpeg"}],"homepage":[{"id":"https://markpbaggett.github.io/canopy-vol-voices/works/1833-aug-18-mouth-of-poplar-creek-to-george-l-welcker-west-point-new-york","type":"Text","label":{"en":["1833 Aug. 18, Mouth of Poplar Creek [to] Geo[rge] L. Welcker, W[est] Point, New York"]}}]}],"partOf":[{"id":"https://markpbaggett.github.io/canopy-vol-voices/api/facet/place.json","type":"Collection"}],"summary":{"none":["Place"]},"homepage":[{"id":"https://markpbaggett.github.io/canopy-vol-voices/search?place=tennessee-politics-and-government-to-1865-2","type":"Text","label":{"none":["Tennessee -- Politics and government -- To 1865 ."]}}]}