{"@context":"https://iiif.io/api/presentation/3/context.json","id":"https://markpbaggett.github.io/canopy-vol-voices/api/facet/place/tennessee-blount-county.json","type":"Collection","label":{"none":["Tennessee -- Blount County."]},"items":[{"id":"https://digital.lib.utk.edu/assemble/manifest/volvoices/4795","type":"Manifest","label":{"en":["John L.T. Sneed in Memphis, Tennessee to O.P. Temple in Knoxville, Tennessee"]},"thumbnail":[{"id":"https://digital.lib.utk.edu/collections/islandora/object/volvoices%3A4795/datastream/TN","width":200,"height":200,"type":"Image","format":"image/jpeg"}],"homepage":[{"id":"https://markpbaggett.github.io/canopy-vol-voices/works/john-lt-sneed-in-memphis-tennessee-to-op-temple-in-knoxville-tennessee","type":"Text","label":{"en":["John L.T. Sneed in Memphis, Tennessee to O.P. Temple in Knoxville, Tennessee"]}}]},{"id":"https://digital.lib.utk.edu/assemble/manifest/volvoices/4805","type":"Manifest","label":{"en":["H. Foster in Sheldon, Illinois to O.P. Temple in Knoxville, Tennessee"]},"thumbnail":[{"id":"https://digital.lib.utk.edu/collections/islandora/object/volvoices%3A4805/datastream/TN","width":200,"height":200,"type":"Image","format":"image/jpeg"}],"homepage":[{"id":"https://markpbaggett.github.io/canopy-vol-voices/works/h-foster-in-sheldon-illinois-to-op-temple-in-knoxville-tennessee","type":"Text","label":{"en":["H. Foster in Sheldon, Illinois to O.P. Temple in Knoxville, Tennessee"]}}]},{"id":"https://digital.lib.utk.edu/assemble/manifest/volvoices/6379","type":"Manifest","label":{"en":["Hannah and Her Children vs. Patrick McClung and James Houston"]},"thumbnail":[{"id":"https://digital.lib.utk.edu/collections/islandora/object/volvoices%3A6379/datastream/TN","width":200,"height":200,"type":"Image","format":"image/jpeg"}],"homepage":[{"id":"https://markpbaggett.github.io/canopy-vol-voices/works/hannah-and-her-children-vs-patrick-mcclung-and-james-houston","type":"Text","label":{"en":["Hannah and Her Children vs. Patrick McClung and James Houston"]}}]},{"id":"https://digital.lib.utk.edu/assemble/manifest/volvoices/6384","type":"Manifest","label":{"en":["Deed of Land from William Blair to John Rosin"]},"thumbnail":[{"id":"https://digital.lib.utk.edu/collections/islandora/object/volvoices%3A6384/datastream/TN","width":200,"height":200,"type":"Image","format":"image/jpeg"}],"homepage":[{"id":"https://markpbaggett.github.io/canopy-vol-voices/works/deed-of-land-from-william-blair-to-john-rosin","type":"Text","label":{"en":["Deed of Land from William Blair to John Rosin"]}}]},{"id":"https://digital.lib.utk.edu/assemble/manifest/volvoices/6390","type":"Manifest","label":{"en":["Bill of Complaint Against Arthur H. Henley [amp] Others, and Reply"]},"thumbnail":[{"id":"https://digital.lib.utk.edu/collections/islandora/object/volvoices%3A6390/datastream/TN","width":200,"height":200,"type":"Image","format":"image/jpeg"}],"homepage":[{"id":"https://markpbaggett.github.io/canopy-vol-voices/works/bill-of-complaint-against-arthur-h-henley-amp-others-and-reply","type":"Text","label":{"en":["Bill of Complaint Against Arthur H. Henley [amp] Others, and Reply"]}}]},{"id":"https://digital.lib.utk.edu/assemble/manifest/volvoices/6658","type":"Manifest","label":{"en":["Hannah and Her Children vs. Patrick McClung and James Houston"]},"thumbnail":[{"id":"https://digital.lib.utk.edu/collections/islandora/object/volvoices%3A6658/datastream/TN","width":200,"height":200,"type":"Image","format":"image/jpeg"}],"homepage":[{"id":"https://markpbaggett.github.io/canopy-vol-voices/works/hannah-and-her-children-vs-patrick-mcclung-and-james-houston-2","type":"Text","label":{"en":["Hannah and Her Children vs. Patrick McClung and James Houston"]}}]},{"id":"https://digital.lib.utk.edu/assemble/manifest/volvoices/6663","type":"Manifest","label":{"en":["Deed of Land from William Blair to John Rosin"]},"thumbnail":[{"id":"https://digital.lib.utk.edu/collections/islandora/object/volvoices%3A6663/datastream/TN","width":200,"height":200,"type":"Image","format":"image/jpeg"}],"homepage":[{"id":"https://markpbaggett.github.io/canopy-vol-voices/works/deed-of-land-from-william-blair-to-john-rosin-2","type":"Text","label":{"en":["Deed of Land from William Blair to John Rosin"]}}]},{"id":"https://digital.lib.utk.edu/assemble/manifest/volvoices/7977","type":"Manifest","label":{"en":["Convention of Teachers"]},"thumbnail":[{"id":"https://digital.lib.utk.edu/collections/islandora/object/volvoices%3A7977/datastream/TN","width":200,"height":200,"type":"Image","format":"image/jpeg"}],"homepage":[{"id":"https://markpbaggett.github.io/canopy-vol-voices/works/convention-of-teachers","type":"Text","label":{"en":["Convention of Teachers"]}}]},{"id":"https://digital.lib.utk.edu/assemble/manifest/volvoices/7986","type":"Manifest","label":{"en":["Circular"]},"thumbnail":[{"id":"https://digital.lib.utk.edu/collections/islandora/object/volvoices%3A7986/datastream/TN","width":200,"height":200,"type":"Image","format":"image/jpeg"}],"homepage":[{"id":"https://markpbaggett.github.io/canopy-vol-voices/works/circular","type":"Text","label":{"en":["Circular"]}}]},{"id":"https://digital.lib.utk.edu/assemble/manifest/volvoices/8392","type":"Manifest","label":{"en":["Railroad ticket from Chilhowee, Tennessee to Montvale, Tennessee"]},"thumbnail":[{"id":"https://digital.lib.utk.edu/collections/islandora/object/volvoices%3A8392/datastream/TN","width":200,"height":200,"type":"Image","format":"image/jpeg"}],"homepage":[{"id":"https://markpbaggett.github.io/canopy-vol-voices/works/railroad-ticket-from-chilhowee-tennessee-to-montvale-tennessee","type":"Text","label":{"en":["Railroad ticket from Chilhowee, Tennessee to Montvale, Tennessee"]}}]},{"id":"https://digital.lib.utk.edu/assemble/manifest/volvoices/8396","type":"Manifest","label":{"en":["Main Street in Maryville, Tennessee"]},"thumbnail":[{"id":"https://digital.lib.utk.edu/collections/islandora/object/volvoices%3A8396/datastream/TN","width":200,"height":200,"type":"Image","format":"image/jpeg"}],"homepage":[{"id":"https://markpbaggett.github.io/canopy-vol-voices/works/main-street-in-maryville-tennessee","type":"Text","label":{"en":["Main Street in Maryville, Tennessee"]}}]},{"id":"https://digital.lib.utk.edu/assemble/manifest/volvoices/11607","type":"Manifest","label":{"en":["Wooden postcard from O'Ledia in Kinzel Springs, Tennessee to Mrs. E.J. Kinzel in Pensacola, Florida"]},"thumbnail":[{"id":"https://digital.lib.utk.edu/collections/islandora/object/volvoices%3A11607/datastream/TN","width":200,"height":200,"type":"Image","format":"image/jpeg"}],"homepage":[{"id":"https://markpbaggett.github.io/canopy-vol-voices/works/wooden-postcard-from-oledia-in-kinzel-springs-tennessee-to-mrs-ej-kinzel-in-pensacola-florida","type":"Text","label":{"en":["Wooden postcard from O'Ledia in Kinzel Springs, Tennessee to Mrs. E.J. Kinzel in Pensacola, Florida"]}}]},{"id":"https://digital.lib.utk.edu/assemble/manifest/volvoices/11611","type":"Manifest","label":{"en":["Tax Dollars"]},"thumbnail":[{"id":"https://digital.lib.utk.edu/collections/islandora/object/volvoices%3A11611/datastream/TN","width":200,"height":200,"type":"Image","format":"image/jpeg"}],"homepage":[{"id":"https://markpbaggett.github.io/canopy-vol-voices/works/tax-dollars","type":"Text","label":{"en":["Tax Dollars"]}}]},{"id":"https://digital.lib.utk.edu/assemble/manifest/volvoices/11614","type":"Manifest","label":{"en":["Photograph of individuals and knitting mill"]},"thumbnail":[{"id":"https://digital.lib.utk.edu/collections/islandora/object/volvoices%3A11614/datastream/TN","width":200,"height":200,"type":"Image","format":"image/jpeg"}],"homepage":[{"id":"https://markpbaggett.github.io/canopy-vol-voices/works/photograph-of-individuals-and-knitting-mill","type":"Text","label":{"en":["Photograph of individuals and knitting mill"]}}]},{"id":"https://digital.lib.utk.edu/assemble/manifest/volvoices/11618","type":"Manifest","label":{"en":["Classes of Maryville Polytechnic School in Maryville, Tennessee"]},"thumbnail":[{"id":"https://digital.lib.utk.edu/collections/islandora/object/volvoices%3A11618/datastream/TN","width":200,"height":200,"type":"Image","format":"image/jpeg"}],"homepage":[{"id":"https://markpbaggett.github.io/canopy-vol-voices/works/classes-of-maryville-polytechnic-school-in-maryville-tennessee","type":"Text","label":{"en":["Classes of Maryville Polytechnic School in Maryville, Tennessee"]}}]},{"id":"https://digital.lib.utk.edu/assemble/manifest/volvoices/11624","type":"Manifest","label":{"en":["Girls basketball team at Maryville Polytechnic School in Tennessee"]},"thumbnail":[{"id":"https://digital.lib.utk.edu/collections/islandora/object/volvoices%3A11624/datastream/TN","width":200,"height":200,"type":"Image","format":"image/jpeg"}],"homepage":[{"id":"https://markpbaggett.github.io/canopy-vol-voices/works/girls-basketball-team-at-maryville-polytechnic-school-in-tennessee","type":"Text","label":{"en":["Girls basketball team at Maryville Polytechnic School in Tennessee"]}}]},{"id":"https://digital.lib.utk.edu/assemble/manifest/volvoices/11627","type":"Manifest","label":{"en":["Girls basketball team at Maryville Polytechnic School in Tennessee"]},"thumbnail":[{"id":"https://digital.lib.utk.edu/collections/islandora/object/volvoices%3A11627/datastream/TN","width":200,"height":200,"type":"Image","format":"image/jpeg"}],"homepage":[{"id":"https://markpbaggett.github.io/canopy-vol-voices/works/girls-basketball-team-at-maryville-polytechnic-school-in-tennessee-2","type":"Text","label":{"en":["Girls basketball team at Maryville Polytechnic School in Tennessee"]}}]},{"id":"https://digital.lib.utk.edu/assemble/manifest/volvoices/11634","type":"Manifest","label":{"en":["Photographs from Maryville Polytechnic School in Tennessee"]},"thumbnail":[{"id":"https://digital.lib.utk.edu/collections/islandora/object/volvoices%3A11634/datastream/TN","width":200,"height":200,"type":"Image","format":"image/jpeg"}],"homepage":[{"id":"https://markpbaggett.github.io/canopy-vol-voices/works/photographs-from-maryville-polytechnic-school-in-tennessee","type":"Text","label":{"en":["Photographs from Maryville Polytechnic School in Tennessee"]}}]},{"id":"https://digital.lib.utk.edu/assemble/manifest/volvoices/11637","type":"Manifest","label":{"en":["Photographs from the Polytechnic High School Yearbook"]},"thumbnail":[{"id":"https://digital.lib.utk.edu/collections/islandora/object/volvoices%3A11637/datastream/TN","width":200,"height":200,"type":"Image","format":"image/jpeg"}],"homepage":[{"id":"https://markpbaggett.github.io/canopy-vol-voices/works/photographs-from-the-polytechnic-high-school-yearbook","type":"Text","label":{"en":["Photographs from the Polytechnic High School Yearbook"]}}]},{"id":"https://digital.lib.utk.edu/assemble/manifest/volvoices/11643","type":"Manifest","label":{"en":["Construction of the Louisville and Nashiville Railroad"]},"thumbnail":[{"id":"https://digital.lib.utk.edu/collections/islandora/object/volvoices%3A11643/datastream/TN","width":200,"height":200,"type":"Image","format":"image/jpeg"}],"homepage":[{"id":"https://markpbaggett.github.io/canopy-vol-voices/works/construction-of-the-louisville-and-nashiville-railroad","type":"Text","label":{"en":["Construction of the Louisville and Nashiville Railroad"]}}]},{"id":"https://digital.lib.utk.edu/assemble/manifest/volvoices/11708","type":"Manifest","label":{"en":["Sam Houston daguerreotype"]},"thumbnail":[{"id":"https://digital.lib.utk.edu/collections/islandora/object/volvoices%3A11708/datastream/TN","width":200,"height":200,"type":"Image","format":"image/jpeg"}],"homepage":[{"id":"https://markpbaggett.github.io/canopy-vol-voices/works/sam-houston-daguerreotype","type":"Text","label":{"en":["Sam Houston daguerreotype"]}}]},{"id":"https://digital.lib.utk.edu/assemble/manifest/volvoices/13462","type":"Manifest","label":{"en":["Minutes of the construction of a new courthouse in Blount County, Tennessee"]},"thumbnail":[{"id":"https://digital.lib.utk.edu/collections/islandora/object/volvoices%3A13462/datastream/TN","width":200,"height":200,"type":"Image","format":"image/jpeg"}],"homepage":[{"id":"https://markpbaggett.github.io/canopy-vol-voices/works/minutes-of-the-construction-of-a-new-courthouse-in-blount-county-tennessee","type":"Text","label":{"en":["Minutes of the construction of a new courthouse in Blount County, Tennessee"]}}]},{"id":"https://digital.lib.utk.edu/assemble/manifest/volvoices/15791","type":"Manifest","label":{"en":["L.C. Houk in Montvale Springs, Tennessee to O.P. Temple in Knoxville, Tennessee"]},"thumbnail":[{"id":"https://digital.lib.utk.edu/collections/islandora/object/volvoices%3A15791/datastream/TN","width":200,"height":200,"type":"Image","format":"image/jpeg"}],"homepage":[{"id":"https://markpbaggett.github.io/canopy-vol-voices/works/lc-houk-in-montvale-springs-tennessee-to-op-temple-in-knoxville-tennessee","type":"Text","label":{"en":["L.C. Houk in Montvale Springs, Tennessee to O.P. Temple in Knoxville, Tennessee"]}}]},{"id":"https://digital.lib.utk.edu/assemble/manifest/volvoices/16028","type":"Manifest","label":{"en":["Jerome Templeton in Sevierville, Tennessee to O.P. Temple in Knoxville, Tennessee"]},"thumbnail":[{"id":"https://digital.lib.utk.edu/collections/islandora/object/volvoices%3A16028/datastream/TN","width":200,"height":200,"type":"Image","format":"image/jpeg"}],"homepage":[{"id":"https://markpbaggett.github.io/canopy-vol-voices/works/jerome-templeton-in-sevierville-tennessee-to-op-temple-in-knoxville-tennessee","type":"Text","label":{"en":["Jerome Templeton in Sevierville, Tennessee to O.P. Temple in Knoxville, Tennessee"]}}]},{"id":"https://digital.lib.utk.edu/assemble/manifest/volvoices/16042","type":"Manifest","label":{"en":["H. Foster in Nashville, Tennessee to O.P. Temple in Knoxville, Tennessee"]},"thumbnail":[{"id":"https://digital.lib.utk.edu/collections/islandora/object/volvoices%3A16042/datastream/TN","width":200,"height":200,"type":"Image","format":"image/jpeg"}],"homepage":[{"id":"https://markpbaggett.github.io/canopy-vol-voices/works/h-foster-in-nashville-tennessee-to-op-temple-in-knoxville-tennessee","type":"Text","label":{"en":["H. Foster in Nashville, Tennessee to O.P. Temple in Knoxville, Tennessee"]}}]}],"partOf":[{"id":"https://markpbaggett.github.io/canopy-vol-voices/api/facet/place.json","type":"Collection"}],"summary":{"none":["Place"]},"homepage":[{"id":"https://markpbaggett.github.io/canopy-vol-voices/search?place=tennessee-blount-county","type":"Text","label":{"none":["Tennessee -- Blount County."]}}]}