{"@context":"https://iiif.io/api/presentation/3/context.json","id":"https://markpbaggett.github.io/canopy-vol-voices/api/facet/place/turn-of-the-century-turn-of-the-century.json","type":"Collection","label":{"none":["Turn-of-the century; Turn of the century."]},"items":[{"id":"https://digital.lib.utk.edu/assemble/manifest/volvoices/11195","type":"Manifest","label":{"en":["Hiwassee College women's basketball team"]},"thumbnail":[{"id":"https://digital.lib.utk.edu/collections/islandora/object/volvoices%3A11195/datastream/TN","width":200,"height":200,"type":"Image","format":"image/jpeg"}],"homepage":[{"id":"https://markpbaggett.github.io/canopy-vol-voices/works/hiwassee-college-womens-basketball-team","type":"Text","label":{"en":["Hiwassee College women's basketball team"]}}]}],"partOf":[{"id":"https://markpbaggett.github.io/canopy-vol-voices/api/facet/place.json","type":"Collection"}],"summary":{"none":["Place"]},"homepage":[{"id":"https://markpbaggett.github.io/canopy-vol-voices/search?place=turn-of-the-century-turn-of-the-century","type":"Text","label":{"none":["Turn-of-the century; Turn of the century."]}}]}